package1/__init__.py
package2/__init__.py
package3/__init__.py
My_Package_126-0.0.0.dist-info/METADATA
My_Package_126-0.0.0.dist-info/WHEEL
My_Package_126-0.0.0.dist-info/top_level.txt
My_Package_126-0.0.0.dist-info/RECORD
