Metadata-Version: 2.1
Name: My-Package-126
Version: 0.0.0
Summary: This is my Package
Author: Me
